emaux_client/__init__.py
emaux_client/pump.py
emaux_client-0.1.1.dist-info/METADATA
emaux_client-0.1.1.dist-info/WHEEL
emaux_client-0.1.1.dist-info/licenses/LICENSE
emaux_client-0.1.1.dist-info/RECORD
